hyo2.enc-1.2.1-py3.8-nspkg.pth
hyo2/encx/__init__.py
hyo2/encx/__main__.py
hyo2/encx/enc_tab.py
hyo2/encx/enc_tree.py
hyo2/encx/encx.py
hyo2/encx/gui.py
hyo2/encx/hcell_tab.py
hyo2/encx/iso_tab.py
hyo2/encx/iso_tree.py
hyo2/encx/mainwin.py
hyo2/encx/s57_tab.py
hyo2/encx/s57_tree.py
hyo2/encx/s57features_tab.py
hyo2/encx/s57features_tree.py
hyo2/encx/media/ENCX.ico
hyo2/encx/media/app_icon.png
hyo2/encx/media/coll.png
hyo2/encx/media/conn_node.png
hyo2/encx/media/dda.png
hyo2/encx/media/ddf.png
hyo2/encx/media/ddr.png
hyo2/encx/media/dir.png
hyo2/encx/media/dr.png
hyo2/encx/media/drs.png
hyo2/encx/media/edge.png
hyo2/encx/media/enc.png
hyo2/encx/media/favicon.png
hyo2/encx/media/file.png
hyo2/encx/media/fld.png
hyo2/encx/media/geo.png
hyo2/encx/media/group1.png
hyo2/encx/media/group2.png
hyo2/encx/media/hcell.png
hyo2/encx/media/iso.png
hyo2/encx/media/isol_node.png
hyo2/encx/media/ldr.png
hyo2/encx/media/meta.png
hyo2/encx/media/obj.png
hyo2/encx/media/objs.png
hyo2/encx/media/rec.png
hyo2/encx/media/recs.png
hyo2/encx/media/s57.png
hyo2/encx/media/sub.png
hyo2/encx/media/tag.png
hyo2/encx/media/uda.png
hyo2/encx/media/vec.png
hyo2/iso8211/__init__.py
hyo2/iso8211/iso8211.cp38-win_amd64.pyd
hyo2/s57/__init__.py
hyo2/s57/s57.cp38-win_amd64.pyd
hyo2.enc-1.2.1.dist-info/AUTHORS.rst
hyo2.enc-1.2.1.dist-info/LICENSE
hyo2.enc-1.2.1.dist-info/METADATA
hyo2.enc-1.2.1.dist-info/WHEEL
hyo2.enc-1.2.1.dist-info/entry_points.txt
hyo2.enc-1.2.1.dist-info/namespace_packages.txt
hyo2.enc-1.2.1.dist-info/top_level.txt
hyo2.enc-1.2.1.dist-info/RECORD
