Metadata-Version: 2.1
Name: hyo2.enc
Version: 1.2.1
Summary: A library and an application to manage S57 files.
Home-page: https://github.com/hydroffice/hyo2_enc
Author: Giuseppe Masetti
Author-email: gmasetti@ccom.unh.edu
License: LGPLv3 license
Keywords: hydrography ocean mapping survey enc chart iso8211
Platform: UNKNOWN
Classifier: Development Status :: 4 - Beta
Classifier: Intended Audience :: Science/Research
Classifier: Natural Language :: English
Classifier: License :: OSI Approved :: GNU Lesser General Public License v3 (LGPLv3)
Classifier: Operating System :: OS Independent
Classifier: Programming Language :: Python
Classifier: Programming Language :: Python :: 3
Classifier: Programming Language :: Python :: 3.6
Classifier: Programming Language :: Python :: 3.7
Classifier: Programming Language :: Python :: 3.8
Classifier: Topic :: Scientific/Engineering :: GIS
Classifier: Topic :: Office/Business :: Office Suites
Requires-Python: >=3.6
License-File: LICENSE
License-File: AUTHORS.rst
Requires-Dist: hyo2.abc
Provides-Extra: encx
Requires-Dist: PySide2 ; extra == 'encx'
